[{"id":"mpvowcpqambu","nombres":"ANDRES ISAAC","apellidos":"PIGUAVE VIEJO","cedula":"0944314228","email":"dianapiguabe@gmail.com","telefono":"0939694541","ciudad":"LA PUNTILLA","convocatoriaId":"mpvlj6x9d6d8","fuente":"referido","referidoPor":"cesar tenemaza ","notas":"","educacion":[{"institucion":"TOMAS RENDON SOLANO","titulo":"CIENCIAS","nivel":"Bachillerato"}],"experiencia":[{"empresa":"HACIENDA MARIXA 2","cargo":"JORNALERO","area":"OPERATIVO","inicio":"2025-01","fin":"2025-05"},{"empresa":"AGRO AZUCAR","cargo":"EMPAQUETADO","area":"OPERATIVO","inicio":"2025-06","fin":"2026-02"}],"habilidades":[],"idiomas":[],"etapa":"postulado","puntajePreseleccion":null,"puntajeSeleccion":null,"puntajeEntrevista":null,"puntajeTotal":null,"decisionDirector":null,"notaDirector":"","justificacion":"","pruebas":[],"entrevistas":[],"cre":"2026-06-01"},{"id":"mpvol3y6ki6l","nombres":"JORGE RONALDO","apellidos":"ORDOÑEZ LUQUE","cedula":"0928936913","email":"ordonezjorge2003@gmail.com","telefono":"0988590830","ciudad":"LA PUNTILLA","convocatoriaId":"mpvlj6x9d6d8","fuente":"referido","referidoPor":"JOHAN VARGAS","notas":"LICENCIA DE CONDUCIR TIPO E","educacion":[{"institucion":"UNIDAD EDUCATIVA ","titulo":"APLICACIONES INFORMATICA","nivel":"Bachillerato"}],"experiencia":[{"empresa":"ENVASADORA DE AGUA YASUNI","cargo":"CHOFER","area":"CHOFER","inicio":"","fin":""}],"habilidades":["MANEJO DE PROGRAMAS INFORMATICOS"],"idiomas":["ESPAÑOL"],"etapa":"postulado","puntajePreseleccion":65,"puntajeSeleccion":null,"puntajeEntrevista":null,"puntajeTotal":null,"decisionDirector":null,"notaDirector":"","justificacion":"","pruebas":[],"entrevistas":[],"cre":"2026-06-01"}]